{
    "widgets": {
        "app-header": {
            "view": "Вид",
            "view.table": "Таблица",
            "profiles": "Профили",
            "profiles.logout": "Выйти",
            "language": "Язык",
            "language.russian": "Русский",
            "language.english": "Английский",
            "payment": "Платёж",
            "payment.table": "Таблица платежей",
            "payment.create": "Создать платёж"
        },
        "data-grid": {
            "rows-per-page-label": "Элементов на странице",
            "info": "Всего"
        }
    },
    "entities": {
        "form-fields": {
            "payment": {
                "amount": {
                    "label": "Введите сумму:",
                    "placeholder": "Сумма",
                    "description": "Введите сумму для продолжения"
                },
                "confirm": {
                    "label": "Платёж подтверждён?",
                    "description": "Вы должны согласиться, чтобы продолжить."
                },
                "paid-at": {
                    "label": "Выберите дату"
                }
            }
        }
    },
    "features": {
        "payment-grid": {
            "id": "ID",
            "amount": "Сумма",
            "status": "Статус",
            "type": "Тип",
            "paidAt": "Дата оплаты",
            "comment": "Комментарий"
        },
        "payment-grid-dropdown-menu": {
            "show-menu": "Показать меню",
            "payment": "Платёж",
            "edit": "Редактировать",
            "delete": "Удалить",
            "payment-status": "Статус платежа",
            "change-status": "Изменить статус",
            "change-type": "Изменить тип",
            "payment-pending": "В ожидании",
            "payment-paid": "Оплачен",
            "payment-canceled": "Отменён",
            "payment-change-type": "Изменить тип",
            "cource": "Курс",
            "package": "Пакет",
            "single": "Разовый"
        },
        "payment": {
            "sheet": {
                "trigger": "Открыть форму",
                "title": "Быстрый платёж",
                "description": "Введите данные о платеже."
            }
        },
        "payment-form": {
            "cancel": "Отмена",
            "reset": "Сбросить",
            "submit": "Отправить"
        }
    }
}
